MANIFEST.in
README.md
setup.cfg
setup.py
ezfacebook/__init__.py
ezfacebook/example_settings.py
ezfacebook/example_urls.py
ezfacebook/settings.py
ezfacebook.egg-info/PKG-INFO
ezfacebook.egg-info/SOURCES.txt
ezfacebook.egg-info/dependency_links.txt
ezfacebook.egg-info/entry_points.txt
ezfacebook.egg-info/top_level.txt
ezfacebook.egg-info/zip-safe
ezfacebook/context/__init__.py
ezfacebook/context/context_processors.py
ezfacebook/context/urls.py
ezfacebook/context/views.py
ezfacebook/context/templatetags/__init__.py
ezfacebook/context/templatetags/_fb_script_template.py
ezfacebook/context/templatetags/_param_parser.py
ezfacebook/context/templatetags/absurl.py
ezfacebook/context/templatetags/fb_script.py
ezfacebook/helpers/__init__.py
ezfacebook/helpers/middleware.py
ezfacebook/lib/__init__.py
ezfacebook/lib/adapter.py
ezfacebook/lib/api.py
ezfacebook/lib/settings.py
ezfacebook/tests/__init__.py
ezfacebook/tests/context/__init__.py
ezfacebook/tests/context/templatetags/__init__.py
ezfacebook/tests/context/templatetags/absurl.py
ezfacebook/tests/context/templatetags/fb_script.py
ezfacebook/tests/helpers/__init__.py
ezfacebook/tests/helpers/middleware.py
ezfacebook/tests/lib/__init__.py
ezfacebook/tests/lib/adapter.py
ezfacebook/tests/user/__init__.py
ezfacebook/tests/user/decorators.py
ezfacebook/user/__init__.py
ezfacebook/user/decorators.py
ezfacebook/user/middleware.py