Metadata-Version: 1.0
Name: ezfacebook
Version: 0.87.0
Summary: Django Tools to use facebook seamlessly without having to build around it.
Home-page: https://github.com/explodes/ezfacebook
Author: Evan Leis
Author-email: engineergod@yahoo.com
License: Apache Software License
Platform: UNKNOWN
Classifier: Programming Language :: Python
Classifier: Programming Language :: Python :: 2.6
Classifier: Development Status :: 4 - Beta
Classifier: Environment :: Other Environment
Classifier: Intended Audience :: Developers
Classifier: License :: OSI Approved :: Apache Software License
Classifier: Operating System :: OS Independent
Classifier: Topic :: Software Development :: Libraries :: Python Modules
Classifier: Framework :: Django
